webview/__init__.py
webview/_version.py
webview/errors.py
webview/event.py
webview/guilib.py
webview/http.py
webview/localization.py
webview/menu.py
webview/py.typed
webview/screen.py
webview/util.py
webview/window.py
webview/dom/__init__.py
webview/dom/classlist.py
webview/dom/dom.py
webview/dom/element.py
webview/dom/event.py
webview/dom/propsdict.py
webview/js/__init__.py
webview/js/alert.py
webview/js/api.py
webview/js/css.py
webview/js/dom_json.py
webview/js/events.py
webview/js/mouse.py
webview/js/npo.py
webview/js/polyfill.py
webview/lib/Microsoft.Web.WebView2.Core.dll
webview/lib/Microsoft.Web.WebView2.WinForms.dll
webview/lib/WebBrowserInterop.x64.dll
webview/lib/WebBrowserInterop.x86.dll
webview/lib/pywebview-android.jar
webview/lib/runtimes/win-arm64/native/WebView2Loader.dll
webview/lib/runtimes/win-x64/native/WebView2Loader.dll
webview/lib/runtimes/win-x86/native/WebView2Loader.dll
webview/platforms/__init__.py
webview/platforms/android.py
webview/platforms/cef.py
webview/platforms/cocoa.py
webview/platforms/edgechromium.py
webview/platforms/gtk.py
webview/platforms/mshtml.py
webview/platforms/qt.py
webview/platforms/winforms.py
ipywebview-5.2.1.dist-info/LICENSE
ipywebview-5.2.1.dist-info/METADATA
ipywebview-5.2.1.dist-info/WHEEL
ipywebview-5.2.1.dist-info/top_level.txt
ipywebview-5.2.1.dist-info/RECORD
